[
  {
    "firstName": "23213",
    "lastName": "213213",
    "email": "213213",
    "phone": "213213213",
    "street": "213213",
    "city": "213213",
    "state": "213213",
    "zipCode": "213213",
    "country": "213213",
    "subject": "11221321",
    "message": "32131321",
    "preferredContact": "email",
    "urgency": "normal",
    "id": 1775433598687,
    "timestamp": "2026-04-05T23:59:58.687Z"
  },
  {
    "firstName": "Tuan Shiyam",
    "lastName": "Jannan",
    "email": "shiyamtj@gmail.com",
    "phone": "+94779505544",
    "street": "10/58 Allendale Road, Mount Albert, Auckland, New Zealand",
    "city": "Mount Albert",
    "state": "SD",
    "zipCode": "1025",
    "country": "New Zealand",
    "subject": "SDSDA",
    "message": "SADads",
    "preferredContact": "email",
    "urgency": "normal",
    "id": 1775436560848,
    "timestamp": "2026-04-06T00:49:20.848Z"
  }
]